grprec/__init__.py
grprec/evaluate.py
grprec/group_generation.py
grprec/model.py
grprec/preprocessing.py
grprec/score_agregation.py
tests/__init__.py
grprec-0.0.2.dist-info/LICENCE.txt
grprec-0.0.2.dist-info/METADATA
grprec-0.0.2.dist-info/WHEEL
grprec-0.0.2.dist-info/top_level.txt
grprec-0.0.2.dist-info/RECORD
