Metadata-Version: 2.1
Name: grprec
Version: 0.0.2
Summary: grprec is a python library for analizing, building, testing group recommendation system approaches
Home-page: UNKNOWN
Author: Rezgui Abdelkader
Author-email: ha_rezgui@esi.dz
License: MIT
Keywords: group recommendation
Platform: UNKNOWN
Classifier: License :: OSI Approved :: MIT License
Classifier: Operating System :: Microsoft :: Windows :: Windows 10
Classifier: Programming Language :: Python :: 3
Classifier: Programming Language :: Python :: 3.8
Classifier: Intended Audience :: Science/Research
Requires-Dist: numpy (~=1.22.3)
Requires-Dist: pandas (~=1.4.2)
Requires-Dist: surprise (~=0.1)
